LICENSE
setup.py
HDpip/LICENSE
HDpip/README.md
HDpip/__init__.py
HDpip/main.py
HDpip.egg-info/PKG-INFO
HDpip.egg-info/SOURCES.txt
HDpip.egg-info/dependency_links.txt
HDpip.egg-info/entry_points.txt
HDpip.egg-info/requires.txt
HDpip.egg-info/top_level.txt
HDpip/core/__init__.py
HDpip/core/base.py
HDpip/core/pip.py