Metadata-Version: 2.4
Name: HDpip
Version: 0.0.2
Summary: 寒冬pip(HDpip)
Home-page: https://gitee.com/handongliren
Author: 寒冬利刃(handongliren(hdlr))
Author-email: 1079489986@qq.com
License: MPL-2.0
Keywords: pip,gui,maliang,hdlr,寒冬利刃,handongliren
Classifier: Development Status :: 1 - Planning
Classifier: Intended Audience :: Developers
Classifier: License :: OSI Approved :: Mozilla Public License 2.0 (MPL 2.0)
Classifier: Intended Audience :: Developers
Classifier: Operating System :: OS Independent
Classifier: Programming Language :: Python :: 3.10
Classifier: Programming Language :: Python :: 3.11
Classifier: Programming Language :: Python :: 3.12
Classifier: Programming Language :: Python :: 3.13
Classifier: Programming Language :: Python :: 3.14
Classifier: Topic :: Software Development :: Build Tools
Requires-Python: >=3.10
License-File: LICENSE
Requires-Dist: pip>=25.2
Requires-Dist: maliang[opt]>=3.1.0
Requires-Dist: pyyaml
Requires-Dist: pipdeptree>=2.0.0
Dynamic: author
Dynamic: author-email
Dynamic: classifier
Dynamic: description
Dynamic: description-content-type
Dynamic: home-page
Dynamic: keywords
Dynamic: license
Dynamic: license-file
Dynamic: requires-dist
Dynamic: requires-python
Dynamic: summary
